k3etcd/__init__.py
k3etcd/client.py
k3etcd/synopsis.py
k3etcd-0.1.3.dist-info/licenses/LICENSE
k3etcd-0.1.3.dist-info/METADATA
k3etcd-0.1.3.dist-info/WHEEL
k3etcd-0.1.3.dist-info/top_level.txt
k3etcd-0.1.3.dist-info/RECORD
